{
  "indexes": [
    {
      "collectionGroup": "audit_logs",
      "queryScope": "COLLECTION",
      "fields": [
        {
          "fieldPath": "user.uid",
          "order": "ASCENDING"
        },
        {
          "fieldPath": "timestamp",
          "order": "DESCENDING"
        }
      ]
    },
    {
      "collectionGroup": "audit_logs",
      "queryScope": "COLLECTION",
      "fields": [
        {
          "fieldPath": "eventType",
          "order": "ASCENDING"
        },
        {
          "fieldPath": "timestamp",
          "order": "DESCENDING"
        }
      ]
    },
    {
      "collectionGroup": "audit_logs",
      "queryScope": "COLLECTION",
      "fields": [
        {
          "fieldPath": "resource.id",
          "order": "ASCENDING"
        },
        {
          "fieldPath": "timestamp",
          "order": "DESCENDING"
        }
      ]
    },
    {
      "collectionGroup": "audit_logs",
      "queryScope": "COLLECTION",
      "fields": [
        {
          "fieldPath": "action.success",
          "order": "ASCENDING"
        },
        {
          "fieldPath": "timestamp",
          "order": "DESCENDING"
        }
      ]
    },
    {
      "collectionGroup": "document_metadata",
      "queryScope": "COLLECTION",
      "fields": [
        {
          "fieldPath": "isActive",
          "order": "ASCENDING"
        },
        {
          "fieldPath": "employeeId",
          "order": "ASCENDING"
        },
        {
          "fieldPath": "uploadedAt",
          "order": "DESCENDING"
        }
      ]
    },
    {
      "collectionGroup": "document_metadata",
      "queryScope": "COLLECTION",
      "fields": [
        {
          "fieldPath": "isActive",
          "order": "ASCENDING"
        },
        {
          "fieldPath": "documentType",
          "order": "ASCENDING"
        },
        {
          "fieldPath": "uploadedAt",
          "order": "DESCENDING"
        }
      ]
    },
    {
      "collectionGroup": "document_metadata",
      "queryScope": "COLLECTION",
      "fields": [
        {
          "fieldPath": "isActive",
          "order": "ASCENDING"
        },
        {
          "fieldPath": "uploadedAt",
          "order": "DESCENDING"
        }
      ]
    },
    {
      "collectionGroup": "users",
      "queryScope": "COLLECTION",
      "fields": [
        {
          "fieldPath": "role",
          "order": "ASCENDING"
        },
        {
          "fieldPath": "isActive",
          "order": "ASCENDING"
        },
        {
          "fieldPath": "createdAt",
          "order": "DESCENDING"
        }
      ]
    },
    {
      "collectionGroup": "users",
      "queryScope": "COLLECTION",
      "fields": [
        {
          "fieldPath": "isActive",
          "order": "ASCENDING"
        },
        {
          "fieldPath": "lastLogin",
          "order": "DESCENDING"
        }
      ]
    }
  ],
  "fieldOverrides": [
    {
      "collectionGroup": "audit_logs",
      "fieldPath": "timestamp",
      "ttl": false,
      "indexes": [
        {
          "order": "ASCENDING",
          "queryScope": "COLLECTION"
        },
        {
          "order": "DESCENDING",
          "queryScope": "COLLECTION"
        }
      ]
    },
    {
      "collectionGroup": "document_metadata",
      "fieldPath": "uploadedAt",
      "ttl": false,
      "indexes": [
        {
          "order": "ASCENDING",
          "queryScope": "COLLECTION"
        },
        {
          "order": "DESCENDING",
          "queryScope": "COLLECTION"
        }
      ]
    }
  ]
}